floorplan_epc_detector/__init__.py
floorplan_epc_detector/predictor.py
floorplan_epc_detector/samclip/app.py
floorplan_epc_detector/samclip/clip/__init__.py
floorplan_epc_detector/samclip/clip/model.py
floorplan_epc_detector/samclip/clip/preprocessor.py
floorplan_epc_detector/samclip/clip/siglip_image_processor.py
floorplan_epc_detector/samclip/clip/siglip_tokenizer.py
floorplan_epc_detector/samclip/clip/tokenizer.py
floorplan_epc_detector/samclip/clip/data/bpe_simple_vocab_16e6.txt.gz
floorplan_epc_detector/samclip/gdino/__init__.py
floorplan_epc_detector/samclip/gdino/gdino_tokenizer.py
floorplan_epc_detector/samclip/gdino/model.py
floorplan_epc_detector/samclip/images/dog.jpg
floorplan_epc_detector/samclip/images/gdino_res.jpg
floorplan_epc_detector/samclip/images/gradio.png
floorplan_epc_detector/samclip/images/lip.png
floorplan_epc_detector/samclip/images/shuttle.jpg
floorplan_epc_detector/samclip/images/wave_planet.webp
floorplan_epc_detector/samclip/output/pred.jpg
floorplan_epc_detector/samclip/output/pred_face.jpg
floorplan_epc_detector/samclip/output/pred_walking.jpg
floorplan_epc_detector/samclip/sam/model.py
floorplan_epc_detector/samclip/tests/__init__.py
floorplan_epc_detector/samclip/tests/unit/__init__.py
floorplan_epc_detector/samclip/tests/unit/_test_sam.py
floorplan_epc_detector/samclip/tests/unit/test_gdino.py
floorplan_epc_detector/samclip/tests/unit/test_lip.py
floorplan_epc_detector/samclip/utils/__init__.py
floorplan_epc_detector/samclip/utils/gdino_transforms.py
floorplan_epc_detector/samclip/utils/gdino_utils.py
floorplan_epc_detector/samclip/utils/sentencepiece_model_pb2_new.py
floorplan_epc_detector/samclip/utils/tokenization_utils.py
floorplan_epc_detector/samclip/utils/tokenization_utils_base.py
floorplan_epc_detector/samclip/utils/tools/__init__.py
floorplan_epc_detector/samclip/utils/tools/backbone_utils.py
floorplan_epc_detector/samclip/utils/tools/constants.py
floorplan_epc_detector/samclip/utils/tools/deprecation.py
floorplan_epc_detector-2.0.5.dist-info/METADATA
floorplan_epc_detector-2.0.5.dist-info/WHEEL
floorplan_epc_detector-2.0.5.dist-info/top_level.txt
floorplan_epc_detector-2.0.5.dist-info/RECORD
