Metadata-Version: 2.4
Name: floorplan-epc-detector
Version: 2.0.5
Summary: A package for making predictions using a custom-trained ONNX floorplan/epc/proprty_image model
Home-page: https://github.com/Resipedia/domusview_epc_floorplan_image_detection
Author: Oliver Brown
Project-URL: Bug Tracker, https://github.com/Resipedia/domusview_epc_floorplan_image_detection/issues
Project-URL: Source, https://github.com/Resipedia/domusview_epc_floorplan_image_detection
Classifier: Programming Language :: Python :: 3
Classifier: License :: OSI Approved :: MIT License
Classifier: Operating System :: OS Independent
Classifier: Development Status :: 4 - Beta
Requires-Python: >=3.7
Requires-Dist: onnxruntime>=1.12.0
Requires-Dist: onnxruntime-extensions
Requires-Dist: numpy>=1.19.0
Requires-Dist: requests>=2.25.0
Requires-Dist: Pillow>=10.0.0
Requires-Dist: tqdm>=4.65.0
Requires-Dist: sentencepiece
Requires-Dist: opencv-python-headless
Requires-Dist: ftfy
Requires-Dist: regex
Requires-Dist: scipy
Requires-Dist: gdown
Requires-Dist: huggingface-hub
Requires-Dist: torch>=2.0.0
Requires-Dist: torchvision>=0.15.0
Dynamic: author
Dynamic: classifier
Dynamic: description
Dynamic: description-content-type
Dynamic: home-page
Dynamic: project-url
Dynamic: requires-dist
Dynamic: requires-python
Dynamic: summary
